embedit/__init__.py
embedit/behaviour/__init__.py
embedit/behaviour/create.py
embedit/behaviour/git.py
embedit/behaviour/openai_tools.py
embedit/behaviour/prompts/__init__.py
embedit/behaviour/prompts/default.py
embedit/behaviour/prompts/transform.py
embedit/behaviour/search/__init__.py
embedit/behaviour/search/pipeline_components/__init__.py
embedit/behaviour/search/pipeline_components/a01_gather/__init__.py
embedit/behaviour/search/pipeline_components/a02_split/__init__.py
embedit/behaviour/search/pipeline_components/a03_process/__init__.py
embedit/behaviour/search/pipeline_components/a03_process/edit/__init__.py
embedit/behaviour/search/pipeline_components/a03_process/search/__init__.py
embedit/behaviour/search/pipeline_components/a04_combine/__init__.py
embedit/behaviour/search/pipeline_components/a05_save/__init__.py
embedit/behaviour/search/pipelines/__init__.py
embedit/behaviour/transform.py
embedit/cli/__init__.py
embedit/structures/__init__.py
embedit/structures/embedding.py
embedit/structures/special_tokens.py
embedit/structures/text_file.py
embedit/utils/__init__.py
embedit/utils/diff.py
embedit/utils/log.py
embedit-0.2.12.dist-info/WHEEL
embedit-0.2.12.dist-info/entry_points.txt
embedit-0.2.12.dist-info/METADATA
embedit-0.2.12.dist-info/RECORD
