Metadata-Version: 2.1
Name: embedit
Version: 0.2.12
Summary: 
License: MIT
Author: IsaacBreen
Author-email: mail@isaacbreen.com
Requires-Python: >=3.9,<4.0
Classifier: License :: OSI Approved :: MIT License
Classifier: Programming Language :: Python :: 3
Classifier: Programming Language :: Python :: 3.9
Classifier: Programming Language :: Python :: 3.10
Classifier: Programming Language :: Python :: 3.11
Requires-Dist: delegatefn (>=0.3.4,<0.4.0)
Requires-Dist: dir2md (>=0.2.1,<0.3.0)
Requires-Dist: gitpython (>=3.1.30,<4.0.0)
Requires-Dist: numpy (>=1.24.2,<2.0.0)
Requires-Dist: openai (>=0.27.2,<0.28.0)
Requires-Dist: rich (>=13.0.0,<14.0.0)
Requires-Dist: tenacity (>=8.1.0,<9.0.0)
Requires-Dist: tiktoken (>=0.3.2,<0.4.0)
